{
  "entityType" : "DEVICE",
  "entity" : {
    "additionalInfo" : {
      "gateway" : false,
      "overwriteActivityTime" : false,
      "description" : ""
    },
    "customerId" : {
      "entityType" : "CUSTOMER",
      "id" : "13814000-1dd2-11b2-8080-808080808080"
    },
    "deviceData" : {
      "configuration" : {
        "type" : "DEFAULT"
      },
      "transportConfiguration" : {
        "type" : "DEFAULT"
      }
    },
    "deviceProfileId" : {
      "entityType" : "DEVICE_PROFILE",
      "id" : "39563170-6f7c-11eb-a649-dd0aae203444"
    },
    "externalId" : null,
    "firmwareId" : null,
    "id" : {
      "entityType" : "DEVICE",
      "id" : "c495ad90-53be-11ef-aa15-a127638e3a77"
    },
    "label" : "",
    "name" : "SN-001",
    "ownerId" : null,
    "softwareId" : null,
    "type" : "default"
  },
  "credentials" : {
    "credentialsId" : "glh3tiFlI0V4hsb6x6Zh",
    "credentialsType" : "ACCESS_TOKEN",
    "credentialsValue" : null
  },
  "attributes" : {
    "SERVER_SCOPE" : [ {
      "booleanValue" : false,
      "doubleValue" : null,
      "jsonValue" : null,
      "key" : "active",
      "lastUpdateTs" : 1722926427931,
      "longValue" : null,
      "strValue" : null
    } ],
    "SHARED_SCOPE" : [ ]
  }
}